{
  "category": "DEFAULT",
  "description": "Register externally implemented authentication service.",
  "docLink": "",
  "templateGroup": "custom-authentication",
  "displayOrder": 2,
  "id": "internal-custom-authentication",
  "tags": [ "Custom" ],
  "image": "",
  "idp": {},
  "endpoint": {
    "uri": "",
    "authentication": {
      "type": "",
      "properties": {}
    }
  },
  "name": "Internal Custom Authentication",
  "services": [],
  "disabled": false,
  "templateId": "internal-custom-authentication"
}
