{
    "create": {
        "image": "assets/images/logos/google.svg",
        "header": "Google",
        "Subheading": "Login users with existing Google accounts.",
        "documentation": "",
        "modal": {
            "form": {
                "fields": [
                    {
                        "index": 0,
                        "ariaLabel": "Google IDP Name",
                        "name": "name",
                        "label": "Name",
                        "type": "text",
                        "required": true,
                        "placeholder": "Enter a name for the connection.",
                        "initialValue": "Google",
                        "data-testid": "google-idp-create-wizard-content-idp-name",
                        "maxLength": "50",
                        "minLength": "3",
                        "width": "13"
                    },
                    {
                        "index": 1,
                        "ariaLabel": "Google Client ID", 
                        "type": "text", 
                        "name": "clientId", 
                        "label": "Client ID",
                        "placeholder": "Enter Client ID from Google application.",
                        "required": true, 
                        "autoComplete": true,
                        "data-testid": "google-idp-create-wizard-content-idp-client-id",
                        "maxLength": "100",
                        "minLength": "3",
                        "width": "13"
                    },
                    {
                        "index": 2,
                        "ariaLabel": "Google Client Secret",
                        "className": "addon-field-wrapper",
                        "type": "password", 
                        "name": "clientSecret", 
                        "label": "Client secret",
                        "placeholder": "Enter Client secret from Google application.",
                        "required": true, 
                        "autoComplete": true,
                        "data-testid": "google-idp-create-wizard-content-idp-client-secret",
                        "maxLength": "100",
                        "minLength": "3",
                        "width": "13"
                    }
                ]
                
            },
            "wizardHelp": {
                "message": {
                    "copyInputFields": [
                        {
                            "description": "Use the following URL as the <strong>Authorized Redirect URI</strong>.",
                            "value": "redirect_uri"
                        }
                    ],
                    "header": "Prerequites",
                    "paragraphs": [
                        "Before you begin, create an <strong>OAuth credential</strong> on the <a href=\"https://console.developers.google.com\" target=\"_blank\" rel=\"noopener noreferrer\">Google developer console</a>, and obtain a <strong>Client ID & secret</strong>."                    ],
                    "link": {
                        "text": "See Google's guide on configuring OAuth Apps.",
                        "url": "https://support.google.com/googleapi/answer/6158849"
                    }
                },
                "fields": [
                    {
                        "fieldName": "Name",
                        "hint": "Provide a unique name for the connection."
                    },
                    {
                        "fieldName": "Client ID",
                        "hint": "Provide the <Code class=\"inline-code\">Client ID</Code> you received from Google when you registered the OAuth app."
                    },
                    {
                        "fieldName": "Client secret",
                        "hint": "Provide the <Code class=\"inline-code\">Client secret</Code> you received from Google when you registered the OAuth app."
                    }
                ]
            }
        },
        "properties": [
            {
                "key": "ClientId",
                "value": ""
            },
            {
                "key": "ClientSecret",
                "value": ""
            },
            {
                "key": "callbackUrl",
                "value": "/commonauth"
            },
            {
                "key": "AdditionalQueryParameters",
                "value": "scope=email openid profile"
            }
        ]
    },
    "edit" : {
        "tabs": {
            "general" : [
                {
                    "index": 0,
                    "displayOrder" : 1,
                    "ariaLabel": "name", 
                    "inputType": "resourceName",
                    "name": "name",
                    "label": "Name",
                    "required": true,
                    "message": "Identity Provider name is required",
                    "placeholder": "Google",
                    "validation": true,
                    "value": "",
                    "maxLength": "50",
                    "minLength": "3",
                    "data-testid": "idp-edit-page-general-settings-form-idp-name",
                    "hint": "Enter a unique name for this connection.",
                    "readOnly": false
                },
                {
                    "index": 1,
                    "displayOrder" : 2,
                    "type": "textarea", 
                    "name" : "description",
                    "ariaLabel" : "description",
                    "label" : "Description",
                    "required": false,
                    "placeholder": "Enter a description of the identity provider.",
                    "value": "",
                    "data-testid": "idp-edit-page-general-settings-form-idp-description",
                    "maxLength": "300",
                    "minLength": "3",
                    "hint": "A text description of the identity provider.",
                    "readOnly": false
                },
                {
                    "index": 2,
                    "displayOrder" : 3,
                    "name": "jwks_endpoint",
                    "ariaLabel": "JWKS Endpoint URL",
                    "inputType": "url",
                    "type": "text",
                    "label": "JWKS Endpoint URL",
                    "required": true,
                    "placeholder": "https://{ oauth-provider-url }/oauth/jwks",
                    "value": "",
                    "data-testid": "",
                    "maxLength": "2048",
                    "minLength": "10",
                    "hint": "A JSON Web Key (JWK) Set is a JSON object that represents a set of JWKs. The JSON object MUST have a keys member, with its value being an array of JWKs.",
                    "readOnly": false
                },
                {
                    "index": 3,
                    "displayOrder" : 4,
                    "type": "certbox",
                    "isJWKSEnabled": "",
                    "isReadOnly": "",
                    "editingIDP": "",
                    "onUpdate": "",
                    "isPEMEnabled": ""
                }
            ],
            "settings": {
                "fields": [
                    {
                        "index": 0,
                        "displayOrder" : 5,
                        "ariaLabel": "Google authenticator client ID",
                        "inputType": "clientId",
                        "type": "text",
                        "name": "ClientId",
                        "label": "Client ID",
                        "placeholder": "Enter Client ID from Google application.",
                        "hint": "The Client ID you received from Google for your OAuth app.",
                        "required": true,
                        "readOnly": false,
                        "value": "",
                        "maxLength": "100",
                        "minLength": "3",
                        "width": "16",
                        "data-testid": "idp-edit-page-authenticator-settings-GoogleOIDCAuthenticator-content-client-id"

                    },
                    {
                        "index": 1,
                        "displayOrder" : 6,
                        "ariaLabel": "Google authenticator client secret",
                        "className": "addon-field-wrapper",
                        "inputType": "password",
                        "type": "password",
                        "name": "ClientSecret",
                        "label": "Client secret",
                        "placeholder": "Enter Client secret from Google application.",
                        "hint": "The Client secret you received from Google for your OAuth app.",
                        "required": true,
                        "readOnly": false,
                        "value": "",
                        "maxLength": "50",
                        "minLength": "3",
                        "width": "16",
                        "data-testid": "idp-edit-page-authenticator-settings-GoogleOIDCAuthenticator-content-client-secret"
                    },
                    {
                        "index": 2,
                        "displayOrder" : 7,
                        "ariaLabel": "Google authenticator authorized redirect URL",
                        "inputType": "copyInput",
                        "type": "text",
                        "name": "callbackUrl",
                        "label": "Authorized redirect URI",
                        "placeholder": "",
                        "hint": "The authorized redirect URI used to obtain Google credentials.",
                        "required": "",
                        "value": "",
                        "readOnly": true,
                        "maxLength": "",
                        "minLength": "",
                        "width": "16",
                        "data-testid": "idp-edit-page-authenticator-settings-GoogleOIDCAuthenticator-content-authorized-redirect-url-wrapper"


                    },
                    {
                        "index": 3,
                        "displayOrder" : 8,
                        "ariaLabel": "Google authenticator additional query parameters",
                        "inputType": "queryParamInput",
                        "type": "text",
                        "name": "AdditionalQueryParameters",
                        "label": "Additional Query Parameters",
                        "placeholder": "Enter additional query parameters.",
                        "hint": "Additional query parameters to be sent to Google.",
                        "required": false,
                        "value": "",
                        "readOnly": false,
                        "maxLength": "1000",
                        "minLength": "0",
                        "width": "16",
                        "data-testid": "idp-edit-page-authenticator-settings-GoogleOIDCAuthenticator-content-additional-query-parameters"
                    
                    },
                    {
                        "index": 4,
                        "displayOrder" : 9,
                        "type": "toggle",
                        "ariaLabel": "Enable Google One Tap as a sign in option",
                        "name": "IsGoogleOneTapEnabled",
                        "required": false,
                        "toggle": "",
                        "label": "Google One Tap",
                        "placeholder": "Google one tap as a sign in option",
                        "hint": "Enabling Google One Tap as a sign in option",
                        "readOnly": true,
                        "data-testid": "idp-edit-page-authenticator-settings-GoogleOIDCAuthenticator-content-google-one-tap"
                    }
                ],
                "scopes": [
                    {
                        "description": "Allows to view user's email address.",
                        "displayName": "email",
                        "icon": "envelope outline"
                    },
                    {
                        "description": "Allows to authenticate using OpenID Connect.",
                        "displayName": "openid",
                        "icon": "openid"
                    },
                    {
                        "description": "Allows to view user's basic profile data.",
                        "displayName": "profile",
                        "icon": "user outline"
                    }
                ]
            },
            "quickStart": "google"
        }
    }
}
